MANIFEST.in
README.rst
confluence.py
setup.py
confluence_rest.egg-info/PKG-INFO
confluence_rest.egg-info/SOURCES.txt
confluence_rest.egg-info/dependency_links.txt
confluence_rest.egg-info/not-zip-safe
confluence_rest.egg-info/top_level.txt