Metadata-Version: 1.1
Name: confluence-rest
Version: 0.1.0
Summary: REST API for confluence
Home-page: http://github.com/funkwerk/confluence-python-cli
Author: Remy from github.com/RaymiiOrg, Stefan Rohe
Author-email: UNKNOWN
License: UNKNOWN
Keywords: confluence rest api
Platform: UNKNOWN
Classifier: License :: OSI Approved :: MIT License
Classifier: Programming Language :: Python :: 3
Classifier: Topic :: Software Development
Classifier: Environment :: Console
Classifier: Operating System :: OS Independent
